poetry_up/__init__.py
poetry_up/__main__.py
poetry_up/console.py
poetry_up/git.py
poetry_up/github.py
poetry_up/poetry.py
poetry_up/update.py
poetry_up-0.4.0.dist-info/entry_points.txt
poetry_up-0.4.0.dist-info/LICENSE
poetry_up-0.4.0.dist-info/WHEEL
poetry_up-0.4.0.dist-info/METADATA
poetry_up-0.4.0.dist-info/RECORD
