Metadata-Version: 2.1
Name: poetry-up
Version: 0.4.0
Summary: Upgrade dependencies using Poetry
Home-page: https://github.com/cjolowicz/poetry-up
License: MIT
Author: Claudio Jolowicz
Author-email: mail@claudiojolowicz.com
Requires-Python: >=3.8,<4.0
Classifier: License :: OSI Approved :: MIT License
Classifier: Programming Language :: Python :: 3
Classifier: Programming Language :: Python :: 3.8
Requires-Dist: click (>=7.0,<8.0)
Requires-Dist: tomlkit (>=0.7.0,<0.8.0)
Project-URL: Changelog, https://github.com/cjolowicz/poetry-up/releases
Project-URL: Documentation, https://poetry-up.readthedocs.io
Project-URL: Repository, https://github.com/cjolowicz/poetry-up
